_4711/_4711.py
_4711/__init__.py
_4711/__version__.py
4711-0.0.2.dist-info/entry_points.txt
4711-0.0.2.dist-info/LICENSE
4711-0.0.2.dist-info/WHEEL
4711-0.0.2.dist-info/METADATA
4711-0.0.2.dist-info/RECORD
