Metadata-Version: 2.1
Name: 4711
Version: 0.0.2
Summary: A collection of CLI tools for working with data structures, parsing and formatting
Home-page: https://github.com/kalaspuff/4711
License: MIT
Keywords: 4711,data structures,data,structure
Author: Carl Oscar Aaro
Author-email: hello@carloscar.com
Requires-Python: >=3.6,<4.0
Classifier: Development Status :: 1 - Planning
Classifier: License :: OSI Approved :: MIT License
Classifier: Programming Language :: Python
Classifier: Programming Language :: Python :: 3
Classifier: Programming Language :: Python :: 3.6
Classifier: Programming Language :: Python :: 3.7
Classifier: Programming Language :: Python :: 3.8
Classifier: Topic :: Software Development
Classifier: Topic :: Software Development :: Build Tools
Classifier: Topic :: Software Development :: Code Generators
Classifier: Topic :: Software Development :: Testing
Classifier: Topic :: System :: Systems Administration
Classifier: Topic :: Utilities
Project-URL: Repository, https://github.com/kalaspuff/4711
